tidyms2_batch_corrector/__init__.py
tidyms2_batch_corrector/batch_corrector.py
tidyms2_batch_corrector/test_batch_corrector.py
tidyms2_batch_corrector-0.1.0.dist-info/METADATA
tidyms2_batch_corrector-0.1.0.dist-info/WHEEL
tidyms2_batch_corrector-0.1.0.dist-info/RECORD
