Metadata-Version: 2.4
Name: tidyms2-batch-corrector
Version: 0.1.0
Summary: Batch corrector plugin for TidyMS2.
Author-email: Gabriel Riquelme <griquelme.chm@gmail.com>
License-Expression: MIT
Requires-Python: >=3.11
Requires-Dist: statsmodels>=0.14.4
Requires-Dist: tidyms2
Provides-Extra: dev
Requires-Dist: commitizen>=3.30.0; extra == 'dev'
Requires-Dist: pre-commit>=4.0.1; extra == 'dev'
Requires-Dist: pyright>=1.1.386; extra == 'dev'
Requires-Dist: pytest-cov>=5.0.0; extra == 'dev'
Requires-Dist: pytest-sugar>=1.0.0; extra == 'dev'
Requires-Dist: pytest>=8.3.3; extra == 'dev'
Requires-Dist: ruff>=0.7.1; extra == 'dev'
